SecureBytes.cp36-win_amd64.pyd
SecureBytes-0.3.4.dist-info/LICENSE.txt
SecureBytes-0.3.4.dist-info/METADATA
SecureBytes-0.3.4.dist-info/WHEEL
SecureBytes-0.3.4.dist-info/top_level.txt
SecureBytes-0.3.4.dist-info/RECORD
