Metadata-Version: 2.1
Name: SecureBytes
Version: 0.3.4
Summary: Clears the contents of bytes or integers containing cryptographic material
Home-page: https://github.com/vidaid/pysecbytes
Author: Erik Aronesty
Author-email: erik@getvida.io
License: MIT
Platform: UNKNOWN
